{
  "backUp": [
    "https://www.seedmm.net",
    "https://www.busjav.net",
    "https://www.buscdn.net",
    "https://www.xwb2uooia5o59avwxb.com",
    "https://www.javbus.com",
    "https://www.busdmm.net",
    "https://www.dmmsee.net",
    "https://www.busjav.cc"
  ],
  "xyz":"https://www.javbus.work",
  "update": {
    "versionCode": 282,
    "versionName": "1.2.12",
    "url": "https://raw.githubusercontent.com/Ccixyj/jbusfile/master/JubsDriver_v1.2.12build463.apk",
    "desc": "JBusDriver 1.2.12 更新!
1.修复欧美数据源问题
"
  },
  "notice": {
    "id": 0,
    "content": "网站被gfw了，翻墙试试。"
  }
}
